webparser/__init__.py
webparser/parser.py
webparser/utils.py
webparser_py-0.3.dist-info/METADATA
webparser_py-0.3.dist-info/RECORD
webparser_py-0.3.dist-info/WHEEL
webparser_py-0.3.dist-info/top_level.txt
