Metadata-Version: 2.1
Name: webparser-py
Version: 0.3
Summary: A web parser wrapper on top of lxml and selectolax
Home-page: https://contentstudio.io
Author: Muhammad Azhar
Author-email: azhar@contentstudio.io
Maintainer: Muhammad Azhar
Maintainer-email: azhar@contentstudio.io
License: MIT License
Platform: UNKNOWN
Provides-Extra: full
Requires-Dist: lxml
Requires-Dist: feedparser
Requires-Dist: requests
Provides-Extra: full
Requires-Dist: urllib3; extra == 'full'
Requires-Dist: certifi; extra == 'full'
